hooks/__init__.py
hooks/asyncio/__init__.py
hooks/asyncio/reducers.py
hooks/asyncio/use.py
hooks/backends/__init__.py
hooks/backends/async_interface.py
hooks/backends/backend_state.py
hooks/backends/interface.py
hooks/backends/memory_backend.py
hooks/backends/python_objects_backend.py
hooks/backends/threadsafe_backend.py
hooks/frame_utils.py
hooks/plugins/__init__.py
hooks/plugins/discovery.py
hooks/plugins/redis_backend.py
hooks/plugins/redux.py
hooks/plugins/redux_async.py
hooks/plugins/zustand.py
hooks/reducers.py
hooks/scope.py
hooks/use.py
hooks/utils.py
python_hooks-0.2.1.dist-info/LICENSE
python_hooks-0.2.1.dist-info/METADATA
python_hooks-0.2.1.dist-info/WHEEL
python_hooks-0.2.1.dist-info/RECORD
