Metadata-Version: 2.1
Name: python-hooks
Version: 0.2.1
Summary: A React inspired way to code in Python
Home-page: https://github.com/amitassaraf/python-hooks
License: MIT
Author: Amit Assaraf
Author-email: amit.assaraf@gmail.com
Requires-Python: >=3.9,<4.0
Classifier: Development Status :: 3 - Alpha
Classifier: Intended Audience :: Developers
Classifier: License :: OSI Approved :: MIT License
Classifier: Operating System :: OS Independent
Classifier: Programming Language :: Python :: 3
Classifier: Programming Language :: Python :: 3.9
Classifier: Programming Language :: Python :: 3.10
Classifier: Programming Language :: Python :: 3.11
Classifier: Topic :: Software Development :: Libraries :: Python Modules
Requires-Dist: dill (>=0.3.7,<0.4.0)
Requires-Dist: pyhashxx (>=0.1.3,<0.2.0)
Requires-Dist: pytest-asyncio (>=0.21.1,<0.22.0)
Requires-Dist: python-box[all] (>=7.0.1,<8.0.0)
Project-URL: Repository, https://github.com/amitassaraf/python-hooks
